hnu_gadget/__init__.py
hnu_gadget/__main__.py
hnu_gadget/application.py
hnu_gadget/hackernews.py
hnu_gadget-0.5.0.dist-info/entry_points.txt
hnu_gadget-0.5.0.dist-info/WHEEL
hnu_gadget-0.5.0.dist-info/METADATA
hnu_gadget-0.5.0.dist-info/RECORD
