Metadata-Version: 2.1
Name: hnu-gadget
Version: 0.5.0
Summary: 
Home-page: https://www.github.com/renantamashiro/hnu-gadget
Author: renantamashiro
Author-email: tamashirorenan@gmail.com
Requires-Python: >=3.7,<4.0
Classifier: Programming Language :: Python :: 3
Classifier: Programming Language :: Python :: 3.7
Classifier: Programming Language :: Python :: 3.8
Requires-Dist: requests (>=2.23.0,<3.0.0)
Project-URL: Repository, https://www.github.com/renantamashiro/hnu-gadget
